drf_chunked_upload/__init__.py
drf_chunked_upload/admin.py
drf_chunked_upload/exceptions.py
drf_chunked_upload/models.py
drf_chunked_upload/serializers.py
drf_chunked_upload/settings.py
drf_chunked_upload/views.py
drf_chunked_upload/management/__init__.py
drf_chunked_upload/management/commands/__init__.py
drf_chunked_upload/management/commands/delete_expired_uploads.py
drf_chunked_upload/migrations/0001_initial.py
drf_chunked_upload/migrations/__init__.py
drf_chunked_upload-0.6.0.dist-info/LICENSE.txt
drf_chunked_upload-0.6.0.dist-info/METADATA
drf_chunked_upload-0.6.0.dist-info/WHEEL
drf_chunked_upload-0.6.0.dist-info/top_level.txt
drf_chunked_upload-0.6.0.dist-info/RECORD
