Metadata-Version: 2.1
Name: drf-chunked-upload
Version: 0.6.0
Summary: Upload large files to Django REST Framework in multiple chunks, with the ability to resume if the upload is interrupted.
Home-page: https://github.com/jkeifer/drf-chunked-upload
Author: Jarrett Keifer
Author-email: jkeifer0@gmail.com
License: MIT-Zero
Requires-Python: >3.7
License-File: LICENSE.txt
Requires-Dist: Django >=2.2
Requires-Dist: djangorestframework >=3.11
